{"instagram.com":{"/":{"csrftoken":{"key":"csrftoken","value":"sZ7T16pPkTi4xsHAKmXFHHkOcqhvqoRG","expires":"2020-05-14T18:54:52.000Z","maxAge":31449600,"domain":"instagram.com","path":"/","secure":true,"hostOnly":false,"creation":"2019-05-16T18:38:37.561Z","lastAccessed":"2019-05-16T18:55:02.932Z"},"rur":{"key":"rur","value":"ATN","domain":"instagram.com","path":"/","secure":true,"httpOnly":true,"hostOnly":false,"creation":"2019-05-16T18:38:37.562Z","lastAccessed":"2019-05-16T18:55:04.271Z"},"mid":{"key":"mid","value":"XN2uLQAEAAHvEXEbYdzReDHozfbb","expires":"2029-05-13T18:38:37.000Z","maxAge":315360000,"domain":"instagram.com","path":"/","secure":true,"hostOnly":false,"creation":"2019-05-16T18:38:37.563Z","lastAccessed":"2019-05-16T18:55:02.932Z"},"ds_user_id":{"key":"ds_user_id","value":"13361941370","expires":"2019-08-14T18:55:04.000Z","maxAge":7776000,"domain":"instagram.com","path":"/","secure":true,"hostOnly":false,"creation":"2019-05-16T18:38:39.058Z","lastAccessed":"2019-05-16T18:55:04.272Z"},"sessionid":{"key":"sessionid","value":"13361941370%3AtOPp2w7yg3Qj5f%3A26","expires":"2020-05-15T18:38:39.000Z","maxAge":31536000,"domain":"instagram.com","path":"/","secure":true,"httpOnly":true,"hostOnly":false,"creation":"2019-05-16T18:38:39.059Z","lastAccessed":"2019-05-16T18:55:02.932Z"}}},"www.instagram.com":{"/":{}}}